base_classifier.py
phrase_classifier.py
chClassifier/__init__.py
chClassifier/base_classifier.py
chClassifier/phrase_classifier.py
chClassifier-0.6.4.dist-info/DESCRIPTION.rst
chClassifier-0.6.4.dist-info/METADATA
chClassifier-0.6.4.dist-info/RECORD
chClassifier-0.6.4.dist-info/WHEEL
chClassifier-0.6.4.dist-info/metadata.json
chClassifier-0.6.4.dist-info/top_level.txt
