Metadata-Version: 2.0
Name: chClassifier
Version: 0.6.4
Summary: Neural Network to classify short strings
Home-page: https://github.com/ekatek/char-classify
Author: Ekate Kuznetsova
Author-email: char-classify@technekate.com
License: MIT
Keywords: deep-learning machine-learning string classifier
Platform: UNKNOWN
Classifier: Development Status :: 3 - Alpha
Classifier: Intended Audience :: Developers
Classifier: Topic :: Software Development :: Libraries
Classifier: Topic :: Text Processing
Classifier: License :: OSI Approved :: MIT License
Classifier: Programming Language :: Python :: 2.7
Classifier: Programming Language :: Python :: 3
Classifier: Programming Language :: Python :: 3.2
Classifier: Programming Language :: Python :: 3.3
Classifier: Programming Language :: Python :: 3.4
Classifier: Programming Language :: Python :: 3.5
Requires-Dist: chainer
Requires-Dist: numpy
